Metadata-Version: 1.0
Name: likelihood-distributions
Version: 101
Summary: Sule package for probability density function
Home-page: UNKNOWN
Author: Shamushideen Sule
Author-email: shaamsule@gmail.com
License: UNKNOWN
Platform: UNKNOWN
